nonebot_plugin_talk_with_chatgpt/__init__.py
nonebot_plugin_talk_with_chatgpt/config.py
nonebot_plugin_talk_with_chatgpt/data_handle.py
nonebot_plugin_talk_with_chatgpt/HYWenHei-85W.ttf
nonebot_plugin_talk_with_chatgpt-0.6.4.dist-info/METADATA
nonebot_plugin_talk_with_chatgpt-0.6.4.dist-info/WHEEL
nonebot_plugin_talk_with_chatgpt-0.6.4.dist-info/RECORD
